Metadata-Version: 2.1
Name: wakanda
Version: 0.7
Summary: This library enable to extract data from various african website into a pandas DataFrame 
Home-page: https://github.com/bvbouba/
Author: Bakayoko vaflaly
Author-email: bvbouba@gmail.com
License: MIT
Download-URL: https://github.com/bvbouba/wakanda/archive/0.7.tar.gz
Keywords: africa,stock,index,price,exchange
Platform: UNKNOWN
Classifier: Development Status :: 3 - Alpha
Classifier: Intended Audience :: Developers
Classifier: Topic :: Software Development :: Build Tools
Classifier: License :: OSI Approved :: MIT License
Classifier: Programming Language :: Python :: 3
Classifier: Programming Language :: Python :: 3.4
Classifier: Programming Language :: Python :: 3.5
Classifier: Programming Language :: Python :: 3.6
